odoo/addons/web_search_with_and/README.rst
odoo/addons/web_search_with_and/__init__.py
odoo/addons/web_search_with_and/__manifest__.py
odoo/addons/web_search_with_and/data/data.xml
odoo/addons/web_search_with_and/static/description/icon.png
odoo/addons/web_search_with_and/static/src/js/search.js
odoo11_addon_web_search_with_and-11.0.1.0.0.dist-info/DESCRIPTION.rst
odoo11_addon_web_search_with_and-11.0.1.0.0.dist-info/METADATA
odoo11_addon_web_search_with_and-11.0.1.0.0.dist-info/RECORD
odoo11_addon_web_search_with_and-11.0.1.0.0.dist-info/WHEEL
odoo11_addon_web_search_with_and-11.0.1.0.0.dist-info/metadata.json
odoo11_addon_web_search_with_and-11.0.1.0.0.dist-info/top_level.txt
